structured_data_generator/__init__.py
structured_data_generator/config/__init__.py
structured_data_generator/config/default_config.py
structured_data_generator/core/__init__.py
structured_data_generator/core/constraints.py
structured_data_generator/core/generators.py
structured_data_generator/core/utils.py
structured_data_generator/io/__init__.py
structured_data_generator/io/csv_handler.py
structured_data_generator/io/json_handler.py
structured_data_generator/profiling/__init__.py
structured_data_generator/profiling/profiler.py
structured_data_generator-1.0.0.dist-info/licenses/LICENSE
structured_data_generator-1.0.0.dist-info/METADATA
structured_data_generator-1.0.0.dist-info/WHEEL
structured_data_generator-1.0.0.dist-info/entry_points.txt
structured_data_generator-1.0.0.dist-info/top_level.txt
structured_data_generator-1.0.0.dist-info/RECORD
