Metadata-Version: 2.4
Name: structured_data_generator
Version: 1.0.0
Summary: A powerful CLI tool to generate realistic synthetic data for testing and development
Requires-Python: >=3.7
License-File: LICENSE
Requires-Dist: pandas>=1.3.0
Requires-Dist: faker>=8.0.0
Requires-Dist: numpy
Dynamic: license-file
